etlx_wrapper/__init__.py
etlx_wrapper-1.0.2.dist-info/licenses/LICENSE
etlx_wrapper-1.0.2.dist-info/METADATA
etlx_wrapper-1.0.2.dist-info/WHEEL
etlx_wrapper-1.0.2.dist-info/top_level.txt
etlx_wrapper-1.0.2.dist-info/RECORD
