Metadata-Version: 2.4
Name: etlx_wrapper
Version: 1.0.2
Summary: Python wrapper for ETLX CLI to run ETL workflows from Python
Author-email: realdatadriven <real.datadriven@gmail.com>
License: MIT License
Project-URL: Homepage, https://github.com/realdatadriven/etlx
Project-URL: Repository, https://github.com/realdatadriven/etlx
Keywords: ETL,duckdb,cli,data-pipeline,wrapper
Requires-Python: >=3.7
License-File: LICENSE
Dynamic: license-file
